{
   "nodes":[
      {
         "id":"2110950",
         "cluster":"1",
         "title":"A History of Western Philosophy",
         "relatedness":"0.6416031476416721"
      },
      {
         "id":"379264",
         "cluster":"1",
         "title":"Abaris the Hyperborean",
         "relatedness":"0.6605042722871506"
      },
      {
         "id":"842",
         "cluster":"1",
         "title":"Aegean Sea",
         "relatedness":"0.5738613572915624"
      },
      {
         "id":"573",
         "cluster":"1",
         "title":"Alchemy",
         "relatedness":"0.6613786186196584"
      },
      {
         "id":"1168",
         "cluster":"1",
         "title":"Anaximander",
         "relatedness":"0.7995214766975139"
      },
      {
         "id":"66540",
         "cluster":"1",
         "title":"Ancient Greece",
         "relatedness":"0.6247677116583654"
      },
      {
         "id":"4831143",
         "cluster":"1",
         "title":"Ancient Greek medicine",
         "relatedness":"0.6484342496247335"
      },
      {
         "id":"171171",
         "cluster":"1",
         "title":"Ancient Greek philosophy",
         "relatedness":"0.7615431029572908"
      },
      {
         "id":"594",
         "cluster":"1",
         "title":"Apollo",
         "relatedness":"0.6062473786781528"
      },
      {
         "id":"67161",
         "cluster":"1",
         "title":"Apollonius of Tyana",
         "relatedness":"0.6918429504353061"
      },
      {
         "id":"243369",
         "cluster":"1",
         "title":"Archytas",
         "relatedness":"0.6708810679360462"
      },
      {
         "id":"252342",
         "cluster":"1",
         "title":"Aristippus",
         "relatedness":"0.6660273664998236"
      },
      {
         "id":"308",
         "cluster":"1",
         "title":"Aristotle",
         "relatedness":"0.6765244120849302"
      },
      {
         "id":"98921",
         "cluster":"1",
         "title":"Aristoxenus",
         "relatedness":"0.7383862669303789"
      },
      {
         "id":"83484",
         "cluster":"1",
         "title":"Asceticism",
         "relatedness":"0.568999701315425"
      },
      {
         "id":"20609622",
         "cluster":"1",
         "title":"Babylon",
         "relatedness":"0.6210384792425094"
      },
      {
         "id":"3861353",
         "cluster":"1",
         "title":"Babylonian mathematics",
         "relatedness":"0.7175172379500785"
      },
      {
         "id":"4487",
         "cluster":"1",
         "title":"Bean",
         "relatedness":"0.5158566411616861"
      },
      {
         "id":"4163",
         "cluster":"1",
         "title":"Bertrand Russell",
         "relatedness":"0.5841509367313082"
      },
      {
         "id":"1067391",
         "cluster":"1",
         "title":"Bias of Priene",
         "relatedness":"0.6791325896923349"
      },
      {
         "id":"356705",
         "cluster":"1",
         "title":"Brewer's Dictionary of Phrase and Fable",
         "relatedness":"0.5284880738840145"
      },
      {
         "id":"6599",
         "cluster":"1",
         "title":"Chaldea",
         "relatedness":"0.614322785683099"
      },
      {
         "id":"6046",
         "cluster":"1",
         "title":"Cicero",
         "relatedness":"0.6299126760904048"
      },
      {
         "id":"252905",
         "cluster":"1",
         "title":"Classical antiquity",
         "relatedness":"0.6051503835137271"
      },
      {
         "id":"6591",
         "cluster":"1",
         "title":"Crete",
         "relatedness":"0.5231866407403841"
      },
      {
         "id":"81177",
         "cluster":"1",
         "title":"Crotone",
         "relatedness":"0.6964250302913964"
      },
      {
         "id":"350137",
         "cluster":"1",
         "title":"Cuneiform script",
         "relatedness":"0.5753801798232456"
      },
      {
         "id":"79077",
         "cluster":"1",
         "title":"Delos",
         "relatedness":"0.6435269156277214"
      },
      {
         "id":"47724",
         "cluster":"1",
         "title":"Dicaearchus",
         "relatedness":"0.6495375581669776"
      },
      {
         "id":"8691",
         "cluster":"1",
         "title":"Divination",
         "relatedness":"0.6324115752228379"
      },
      {
         "id":"8632",
         "cluster":"1",
         "title":"Druze",
         "relatedness":"0.5538260740913374"
      },
      {
         "id":"10109",
         "cluster":"1",
         "title":"Esotericism",
         "relatedness":"0.645406897775751"
      },
      {
         "id":"9258",
         "cluster":"1",
         "title":"Ethics",
         "relatedness":"0.5443786795852789"
      },
      {
         "id":"37004",
         "cluster":"1",
         "title":"Greco-Roman mysteries",
         "relatedness":"0.6827205739420514"
      },
      {
         "id":"4385475",
         "cluster":"1",
         "title":"Greek astronomy",
         "relatedness":"0.6777685746941282"
      },
      {
         "id":"539937",
         "cluster":"1",
         "title":"Greek colony",
         "relatedness":"0.5331506310600507"
      },
      {
         "id":"97052",
         "cluster":"1",
         "title":"Heliopolis (ancient)",
         "relatedness":"0.5379768102364013"
      },
      {
         "id":"171867",
         "cluster":"1",
         "title":"Heraclides Ponticus",
         "relatedness":"0.7366519985499261"
      },
      {
         "id":"68928",
         "cluster":"1",
         "title":"Hermes Trismegistus",
         "relatedness":"0.7166498057452753"
      },
      {
         "id":"13574",
         "cluster":"1",
         "title":"Herodotus",
         "relatedness":"0.6594208578939411"
      },
      {
         "id":"732860",
         "cluster":"1",
         "title":"Iamblichus",
         "relatedness":"0.7621759599773158"
      },
      {
         "id":"1848052",
         "cluster":"1",
         "title":"Indian mathematics",
         "relatedness":"0.6827077143364553"
      },
      {
         "id":"340504",
         "cluster":"1",
         "title":"Ionians",
         "relatedness":"0.6794881286804026"
      },
      {
         "id":"168260",
         "cluster":"1",
         "title":"Isocrates",
         "relatedness":"0.624950527834167"
      },
      {
         "id":"674577",
         "cluster":"1",
         "title":"Jabir ibn Hayyan",
         "relatedness":"0.6510341961367369"
      },
      {
         "id":"2002484",
         "cluster":"1",
         "title":"Late Period of ancient Egypt",
         "relatedness":"0.5711977743099564"
      },
      {
         "id":"61963",
         "cluster":"1",
         "title":"List of Greek mythological figures",
         "relatedness":"0.6670074377328987"
      },
      {
         "id":"207217",
         "cluster":"1",
         "title":"Magi",
         "relatedness":"0.6519296147980969"
      },
      {
         "id":"45333",
         "cluster":"1",
         "title":"Magna Graecia",
         "relatedness":"0.6927957847873181"
      },
      {
         "id":"18902",
         "cluster":"1",
         "title":"Mathematician",
         "relatedness":"0.5372296042594061"
      },
      {
         "id":"18831",
         "cluster":"1",
         "title":"Mathematics",
         "relatedness":"0.5012457157834864"
      },
      {
         "id":"2062173",
         "cluster":"1",
         "title":"Metapontum",
         "relatedness":"0.6694527508235071"
      },
      {
         "id":"53141",
         "cluster":"1",
         "title":"Metempsychosis",
         "relatedness":"0.6600613101555224"
      },
      {
         "id":"64222",
         "cluster":"1",
         "title":"Milo of Croton",
         "relatedness":"0.6776053890095273"
      },
      {
         "id":"492229",
         "cluster":"1",
         "title":"Monochord",
         "relatedness":"0.6325911637816397"
      },
      {
         "id":"1977435",
         "cluster":"1",
         "title":"Moralia",
         "relatedness":"0.5927990684797471"
      },
      {
         "id":"4116363",
         "cluster":"1",
         "title":"Music of ancient Greece",
         "relatedness":"0.6449424799860168"
      },
      {
         "id":"318648",
         "cluster":"1",
         "title":"Musica universalis",
         "relatedness":"0.7257807999803645"
      },
      {
         "id":"29174999",
         "cluster":"1",
         "title":"Mysticism",
         "relatedness":"0.5893213144543406"
      },
      {
         "id":"382251",
         "cluster":"1",
         "title":"Natural philosophy",
         "relatedness":"0.7049986071478864"
      },
      {
         "id":"23385833",
         "cluster":"1",
         "title":"Neoplatonism",
         "relatedness":"0.7360789831523709"
      },
      {
         "id":"1128528",
         "cluster":"1",
         "title":"Neopythagoreanism",
         "relatedness":"0.7264651325771045"
      },
      {
         "id":"21137",
         "cluster":"1",
         "title":"Numerology",
         "relatedness":"0.7001050005340894"
      },
      {
         "id":"1403568",
         "cluster":"1",
         "title":"Orphism (religion)",
         "relatedness":"0.6810517697609638"
      },
      {
         "id":"841452",
         "cluster":"1",
         "title":"Pherecydes of Syros",
         "relatedness":"0.7512803523835881"
      },
      {
         "id":"13692155",
         "cluster":"1",
         "title":"Philosophy",
         "relatedness":"0.5541665841660619"
      },
      {
         "id":"4676511",
         "cluster":"1",
         "title":"Phlius",
         "relatedness":"0.5508728958676994"
      },
      {
         "id":"24202",
         "cluster":"1",
         "title":"Phoenicia",
         "relatedness":"0.5738613572915624"
      },
      {
         "id":"22954",
         "cluster":"1",
         "title":"Plato",
         "relatedness":"0.7205876164166645"
      },
      {
         "id":"24517",
         "cluster":"1",
         "title":"Plutarch",
         "relatedness":"0.6511673556413374"
      },
      {
         "id":"455361",
         "cluster":"1",
         "title":"Polycrates",
         "relatedness":"0.6898562810950611"
      },
      {
         "id":"794399",
         "cluster":"1",
         "title":"Porphyry (philosopher)",
         "relatedness":"0.7526719820332808"
      },
      {
         "id":"30340",
         "cluster":"1",
         "title":"Pre-Socratic philosophy",
         "relatedness":"0.7700554439389743"
      },
      {
         "id":"177721",
         "cluster":"1",
         "title":"Pythagorean comma",
         "relatedness":"0.6682716690236411"
      },
      {
         "id":"26513034",
         "cluster":"1",
         "title":"Pythagorean theorem",
         "relatedness":"0.7295570914667924"
      },
      {
         "id":"291170",
         "cluster":"1",
         "title":"Pythagoreanism",
         "relatedness":"0.8227579605206381"
      },
      {
         "id":"53258",
         "cluster":"1",
         "title":"Pythia",
         "relatedness":"0.6562083848651177"
      },
      {
         "id":"243824",
         "cluster":"1",
         "title":"R. M. Hare",
         "relatedness":"0.5155449098889353"
      },
      {
         "id":"25806",
         "cluster":"1",
         "title":"Reincarnation",
         "relatedness":"0.6244620056302578"
      },
      {
         "id":"49972",
         "cluster":"1",
         "title":"Rosicrucianism",
         "relatedness":"0.6798686079289702"
      },
      {
         "id":"46754",
         "cluster":"1",
         "title":"Sacred geometry",
         "relatedness":"0.6649586040116859"
      },
      {
         "id":"3333684",
         "cluster":"1",
         "title":"Samos",
         "relatedness":"0.6880855662192364"
      },
      {
         "id":"26700",
         "cluster":"1",
         "title":"Science",
         "relatedness":"0.509788546277322"
      },
      {
         "id":"28297",
         "cluster":"1",
         "title":"Soul",
         "relatedness":"0.5983229512557059"
      },
      {
         "id":"36487",
         "cluster":"1",
         "title":"Sparta",
         "relatedness":"0.598760589249347"
      },
      {
         "id":"191464",
         "cluster":"1",
         "title":"Sybaris",
         "relatedness":"0.6557616028474984"
      },
      {
         "id":"56148",
         "cluster":"1",
         "title":"Taranto",
         "relatedness":"0.5894378595026769"
      },
      {
         "id":"1570530",
         "cluster":"1",
         "title":"Tetractys",
         "relatedness":"0.7009795857133676"
      },
      {
         "id":"30072",
         "cluster":"1",
         "title":"Thales",
         "relatedness":"0.810671065693759"
      },
      {
         "id":"1607411",
         "cluster":"1",
         "title":"The Republic (Plato)",
         "relatedness":"0.6680877199530644"
      },
      {
         "id":"936952",
         "cluster":"1",
         "title":"Theano (philosopher)",
         "relatedness":"0.681064902496793"
      },
      {
         "id":"69035",
         "cluster":"1",
         "title":"Thoth",
         "relatedness":"0.6278082788653148"
      },
      {
         "id":"30058",
         "cluster":"1",
         "title":"Trojan War",
         "relatedness":"0.5857261200121455"
      },
      {
         "id":"153945",
         "cluster":"1",
         "title":"Vow",
         "relatedness":"0.5453923314775599"
      },
      {
         "id":"13704154",
         "cluster":"1",
         "title":"Western philosophy",
         "relatedness":"0.6569359968684766"
      },
      {
         "id":"223339",
         "cluster":"1",
         "title":"Xenophanes",
         "relatedness":"0.755977410266038"
      },
      {
         "id":"id",
         "cluster":"1",
         "title":"title",
         "relatedness":"relatedness"
      },
      {
         "id":"2685",
         "cluster":"1",
         "title":"Abdera Thrace",
         "relatedness":"0.7915199823620525"
      },
      {
         "id":"862898",
         "cluster":"2",
         "title":"Absolute time and space",
         "relatedness":"0.6672581874322139"
      },
      {
         "id":"1737",
         "cluster":"2",
         "title":"Anaxagoras",
         "relatedness":"0.8363200988089976"
      },
      {
         "id":"470031",
         "cluster":"2",
         "title":"Anecdote",
         "relatedness":"0.5802197895089702"
      },
      {
         "id":"620653",
         "cluster":"2",
         "title":"Apollodorus",
         "relatedness":"0.6625294609566587"
      },
      {
         "id":"1216",
         "cluster":"2",
         "title":"Athens",
         "relatedness":"0.5078126607081992"
      },
      {
         "id":"902",
         "cluster":"2",
         "title":"Atom",
         "relatedness":"0.6631931497061192"
      },
      {
         "id":"2844",
         "cluster":"2",
         "title":"Atomic theory",
         "relatedness":"0.7924866329506831"
      },
      {
         "id":"5756554",
         "cluster":"2",
         "title":"Atomism",
         "relatedness":"0.8899409781472871"
      },
      {
         "id":"15667214",
         "cluster":"2",
         "title":"Bibliotheca historica",
         "relatedness":"0.5689183157309515"
      },
      {
         "id":"692207",
         "cluster":"2",
         "title":"Blinding",
         "relatedness":"0.6024639997422234"
      },
      {
         "id":"547420",
         "cluster":"2",
         "title":"Circa",
         "relatedness":"0.5253940971009647"
      },
      {
         "id":"782427",
         "cluster":"2",
         "title":"Cone (geometry)",
         "relatedness":"0.577519145452525"
      },
      {
         "id":"2582448",
         "cluster":"2",
         "title":"Cosmic pluralism",
         "relatedness":"0.7188670825324923"
      },
      {
         "id":"859283",
         "cluster":"2",
         "title":"Cylinder (geometry)",
         "relatedness":"0.5454125540305599"
      },
      {
         "id":"272167",
         "cluster":"2",
         "title":"De rerum natura",
         "relatedness":"0.7521544450468121"
      },
      {
         "id":"2398094",
         "cluster":"2",
         "title":"Democritus University of Thrace",
         "relatedness":"0.7144218801192832"
      },
      {
         "id":"99425",
         "cluster":"2",
         "title":"Diodorus Siculus",
         "relatedness":"0.5731696581603622"
      },
      {
         "id":"1180105",
         "cluster":"2",
         "title":"Egyptian mathematics",
         "relatedness":"0.5738144004878518"
      },
      {
         "id":"10073",
         "cluster":"2",
         "title":"Epicurus",
         "relatedness":"0.8671574398094801"
      },
      {
         "id":"724601",
         "cluster":"2",
         "title":"Fortuna",
         "relatedness":"0.6615014853533052"
      },
      {
         "id":"8347",
         "cluster":"2",
         "title":"Greek drachma",
         "relatedness":"0.5795550761959087"
      },
      {
         "id":"6266257",
         "cluster":"2",
         "title":"Hermann Alexander Diels",
         "relatedness":"0.7284296996928117"
      },
      {
         "id":"13486",
         "cluster":"2",
         "title":"Hippocrates",
         "relatedness":"0.7220058783467134"
      },
      {
         "id":"14627",
         "cluster":"2",
         "title":"Isaac Newton",
         "relatedness":"0.6491770280334401"
      },
      {
         "id":"4147143",
         "cluster":"2",
         "title":"John Burnet (classicist)",
         "relatedness":"0.7284296996928117"
      },
      {
         "id":"44112",
         "cluster":"2",
         "title":"John Dalton",
         "relatedness":"0.7568762979727915"
      },
      {
         "id":"561941",
         "cluster":"2",
         "title":"Kanada",
         "relatedness":"0.7603165276457737"
      },
      {
         "id":"17924",
         "cluster":"2",
         "title":"Leucippus",
         "relatedness":"0.8829555858752104"
      },
      {
         "id":"690316",
         "cluster":"2",
         "title":"List of ancient Milesians",
         "relatedness":"0.5975419071423698"
      },
      {
         "id":"1738950",
         "cluster":"2",
         "title":"Lives and Opinions of Eminent Philosophers",
         "relatedness":"0.7003043365950324"
      },
      {
         "id":"37145",
         "cluster":"2",
         "title":"Lucretius",
         "relatedness":"0.8145701825401164"
      },
      {
         "id":"19376",
         "cluster":"2",
         "title":"Materialism",
         "relatedness":"0.6866479038427777"
      },
      {
         "id":"395107",
         "cluster":"2",
         "title":"Mechanism (philosophy)",
         "relatedness":"0.7408196379846586"
      },
      {
         "id":"582988",
         "cluster":"2",
         "title":"Meroe",
         "relatedness":"0.5533371443914934"
      },
      {
         "id":"1760214",
         "cluster":"2",
         "title":"Natural phenomenon",
         "relatedness":"0.5793300030000328"
      },
      {
         "id":"332902",
         "cluster":"2",
         "title":"Olympiad",
         "relatedness":"0.6728922500496926"
      },
      {
         "id":"2281137",
         "cluster":"2",
         "title":"Ostanes",
         "relatedness":"0.7340019871217529"
      },
      {
         "id":"23575",
         "cluster":"2",
         "title":"Parmenides",
         "relatedness":"0.8130080648795733"
      },
      {
         "id":"248171",
         "cluster":"2",
         "title":"Petronius",
         "relatedness":"0.5922792822022505"
      },
      {
         "id":"87868",
         "cluster":"2",
         "title":"Posidonius",
         "relatedness":"0.7278788233005739"
      },
      {
         "id":"283007",
         "cluster":"2",
         "title":"Prism (geometry)",
         "relatedness":"0.5847686376949165"
      },
      {
         "id":"23704",
         "cluster":"2",
         "title":"Pyramid",
         "relatedness":"0.5172926266161442"
      },
      {
         "id":"25532",
         "cluster":"2",
         "title":"Renaissance",
         "relatedness":"0.515728245805086"
      },
      {
         "id":"105309",
         "cluster":"2",
         "title":"Satyricon",
         "relatedness":"0.5354101143339662"
      },
      {
         "id":"177582",
         "cluster":"2",
         "title":"Sextus Empiricus",
         "relatedness":"0.7634691509813191"
      },
      {
         "id":"25664190",
         "cluster":"2",
         "title":"Socrates",
         "relatedness":"0.7238432739555936"
      },
      {
         "id":"357356",
         "cluster":"2",
         "title":"Stanford Encyclopedia of Philosophy",
         "relatedness":"0.6023880009322542"
      },
      {
         "id":"52121",
         "cluster":"2",
         "title":"Strabo",
         "relatedness":"0.5580347699731832"
      },
      {
         "id":"2794118",
         "cluster":"2",
         "title":"Teos",
         "relatedness":"0.6881858482908192"
      },
      {
         "id":"98409",
         "cluster":"2",
         "title":"Theophrastus",
         "relatedness":"0.7591161541331883"
      },
      {
         "id":"36857",
         "cluster":"2",
         "title":"Thrace",
         "relatedness":"0.5832624958774828"
      },
      {
         "id":"2068728",
         "cluster":"2",
         "title":"Thrasyllus of Mendes",
         "relatedness":"0.7106126916095001"
      },
      {
         "id":"21391464",
         "cluster":"2",
         "title":"Topos",
         "relatedness":"0.5996792439881455"
      },
      {
         "id":"307366",
         "cluster":"2",
         "title":"Vaisheshika",
         "relatedness":"0.7492042443743117"
      },
      {
         "id":"32498",
         "cluster":"2",
         "title":"Volume",
         "relatedness":"0.5463482078384988"
      },
      {
         "id":"46289",
         "cluster":"2",
         "title":"Xerxes I of Persia",
         "relatedness":"0.6484569132222768"
      },
      {
         "id":"143331",
         "cluster":"2",
         "title":"Zeno of Elea",
         "relatedness":"0.8010760542113754"
      },
      {
         "id":"1544",
         "cluster":"2",
         "title":"Agamemnon",
         "relatedness":"0.6218641803454983"
      },
      {
         "id":"1549",
         "cluster":"4",
         "title":"Agathon",
         "relatedness":"0.7732150306168516"
      },
      {
         "id":"61322",
         "cluster":"4",
         "title":"Alcibiades",
         "relatedness":"0.7469739013537938"
      },
      {
         "id":"98367",
         "cluster":"4",
         "title":"Antisthenes",
         "relatedness":"0.8090638611821409"
      },
      {
         "id":"1174",
         "cluster":"4",
         "title":"Aphrodite",
         "relatedness":"0.5165024011984077"
      },
      {
         "id":"85436",
         "cluster":"4",
         "title":"Attic Greek",
         "relatedness":"0.577023799381168"
      },
      {
         "id":"302613",
         "cluster":"4",
         "title":"Attica",
         "relatedness":"0.5749588030816335"
      },
      {
         "id":"296018",
         "cluster":"4",
         "title":"Critias",
         "relatedness":"0.7856315114005384"
      },
      {
         "id":"7951",
         "cluster":"4",
         "title":"Delphi",
         "relatedness":"0.6106862216427451"
      },
      {
         "id":"6266436",
         "cluster":"4",
         "title":"Diels-Kranz",
         "relatedness":"0.7038915662526177"
      },
      {
         "id":"1250251",
         "cluster":"4",
         "title":"Doxography",
         "relatedness":"0.6981192401873191"
      },
      {
         "id":"591116",
         "cluster":"4",
         "title":"Eleatics",
         "relatedness":"0.8193247550367888"
      },
      {
         "id":"9553",
         "cluster":"4",
         "title":"Empedocles",
         "relatedness":"0.7858509006703615"
      },
      {
         "id":"4202524",
         "cluster":"4",
         "title":"Epideictic",
         "relatedness":"0.8025783446893925"
      },
      {
         "id":"1178825",
         "cluster":"4",
         "title":"Gorgias (dialogue)",
         "relatedness":"0.836068462949139"
      },
      {
         "id":"63444",
         "cluster":"4",
         "title":"Helen of Troy",
         "relatedness":"0.6199435232883228"
      },
      {
         "id":"13208",
         "cluster":"4",
         "title":"Hera",
         "relatedness":"0.5495862731885246"
      },
      {
         "id":"18490",
         "cluster":"4",
         "title":"Larissa",
         "relatedness":"0.6394505684590723"
      },
      {
         "id":"26630411",
         "cluster":"4",
         "title":"Lentini",
         "relatedness":"0.7418692485435604"
      },
      {
         "id":"154997",
         "cluster":"4",
         "title":"Lost work",
         "relatedness":"0.732410178838381"
      },
      {
         "id":"46299",
         "cluster":"4",
         "title":"Menelaus",
         "relatedness":"0.6343459156488389"
      },
      {
         "id":"10916048",
         "cluster":"4",
         "title":"Menexenus",
         "relatedness":"0.7833364103130014"
      },
      {
         "id":"21663",
         "cluster":"4",
         "title":"Nihilism",
         "relatedness":"0.551626002233395"
      },
      {
         "id":"60686",
         "cluster":"4",
         "title":"Nihilist",
         "relatedness":"0.6781865482126846"
      },
      {
         "id":"22537",
         "cluster":"4",
         "title":"Odysseus",
         "relatedness":"0.5887255549579715"
      },
      {
         "id":"36812",
         "cluster":"4",
         "title":"Pericles",
         "relatedness":"0.7262321223156234"
      },
      {
         "id":"80271",
         "cluster":"4",
         "title":"Philostratus",
         "relatedness":"0.7726659561352092"
      },
      {
         "id":"24086",
         "cluster":"4",
         "title":"Protagoras",
         "relatedness":"0.8730601511982513"
      },
      {
         "id":"25447",
         "cluster":"4",
         "title":"Rhetoric",
         "relatedness":"0.6732003655116786"
      },
      {
         "id":"23939752",
         "cluster":"4",
         "title":"Sophism",
         "relatedness":"0.8060564145965303"
      },
      {
         "id":"9393762",
         "cluster":"4",
         "title":"Southern Illinois University Press",
         "relatedness":"0.6809660452136008"
      },
      {
         "id":"78815",
         "cluster":"4",
         "title":"Suda",
         "relatedness":"0.673738593380198"
      },
      {
         "id":"28441",
         "cluster":"4",
         "title":"Syracuse Sicily",
         "relatedness":"0.6184777230280556"
      },
      {
         "id":"74673",
         "cluster":"4",
         "title":"Telemachus",
         "relatedness":"0.640507469681953"
      },
      {
         "id":"55804",
         "cluster":"4",
         "title":"Thessaly",
         "relatedness":"0.5588358111125056"
      },
      {
         "id":"30864",
         "cluster":"4",
         "title":"Thucydides",
         "relatedness":"0.6730726927079262"
      },
      {
         "id":"9735736",
         "cluster":"4",
         "title":"University of South Carolina Press",
         "relatedness":"0.6824539359205452"
      },
      {
         "id":"30927438",
         "cluster":"4",
         "title":"Achaemenid Empire",
         "relatedness":"0.543197042788502"
      },
      {
         "id":"148363",
         "cluster":"5",
         "title":"Ancient Greek",
         "relatedness":"0.5413273471827904"
      },
      {
         "id":"256799",
         "cluster":"5",
         "title":"Aphorism",
         "relatedness":"0.6647366402117068"
      },
      {
         "id":"78336",
         "cluster":"5",
         "title":"Archilochus",
         "relatedness":"0.7112593744264282"
      },
      {
         "id":"2905",
         "cluster":"5",
         "title":"Artemis",
         "relatedness":"0.5554549016717987"
      },
      {
         "id":"2266434",
         "cluster":"5",
         "title":"Best of all possible worlds",
         "relatedness":"0.6331611647819314"
      },
      {
         "id":"219168",
         "cluster":"5",
         "title":"Church Fathers",
         "relatedness":"0.5812838039355139"
      },
      {
         "id":"171297",
         "cluster":"5",
         "title":"Cleanthes",
         "relatedness":"0.7253956223012543"
      },
      {
         "id":"7342",
         "cluster":"5",
         "title":"Clement of Alexandria",
         "relatedness":"0.6626448798037462"
      },
      {
         "id":"38737",
         "cluster":"5",
         "title":"Cosmos",
         "relatedness":"0.7268893326091334"
      },
      {
         "id":"6166042",
         "cluster":"5",
         "title":"Cratylus",
         "relatedness":"0.7388385040205425"
      },
      {
         "id":"2211169",
         "cluster":"5",
         "title":"Cratylus (dialogue)",
         "relatedness":"0.7209623015389626"
      },
      {
         "id":"52813",
         "cluster":"5",
         "title":"Dialectic",
         "relatedness":"0.7120200038844138"
      },
      {
         "id":"724627",
         "cluster":"5",
         "title":"Dialectical monism",
         "relatedness":"0.7321454703797035"
      },
      {
         "id":"219366",
         "cluster":"5",
         "title":"Donato Bramante",
         "relatedness":"0.6656173629779143"
      },
      {
         "id":"8135",
         "cluster":"5",
         "title":"Dualism",
         "relatedness":"0.7196533347296719"
      },
      {
         "id":"9843",
         "cluster":"5",
         "title":"Ephesus",
         "relatedness":"0.6783962130354709"
      },
      {
         "id":"2877300",
         "cluster":"5",
         "title":"Floruit",
         "relatedness":"0.5460279871613714"
      },
      {
         "id":"12598",
         "cluster":"5",
         "title":"Georg Wilhelm Friedrich Hegel",
         "relatedness":"0.6981716175516036"
      },
      {
         "id":"455379",
         "cluster":"5",
         "title":"Hellenistic period",
         "relatedness":"0.6463607647606976"
      },
      {
         "id":"20611083",
         "cluster":"5",
         "title":"Heresy",
         "relatedness":"0.5110881525036353"
      },
      {
         "id":"13700",
         "cluster":"5",
         "title":"Hesiod",
         "relatedness":"0.6773813738076832"
      },
      {
         "id":"724911",
         "cluster":"5",
         "title":"Hippolytus of Rome",
         "relatedness":"0.6425967224467999"
      },
      {
         "id":"13633",
         "cluster":"5",
         "title":"Homer",
         "relatedness":"0.6101406270550802"
      },
      {
         "id":"46401",
         "cluster":"5",
         "title":"Ionia",
         "relatedness":"0.7113329613265493"
      },
      {
         "id":"2529261",
         "cluster":"5",
         "title":"Ionian School (philosophy)",
         "relatedness":"0.71963272007617"
      },
      {
         "id":"7499245",
         "cluster":"5",
         "title":"Juvenal",
         "relatedness":"0.6449026837648028"
      },
      {
         "id":"3125551",
         "cluster":"5",
         "title":"Knucklebones",
         "relatedness":"0.6073045726350639"
      },
      {
         "id":"1023023",
         "cluster":"5",
         "title":"Liniment",
         "relatedness":"0.5579118381283068"
      },
      {
         "id":"319762",
         "cluster":"5",
         "title":"Logos",
         "relatedness":"0.7816834469166378"
      },
      {
         "id":"165457",
         "cluster":"5",
         "title":"Lucian",
         "relatedness":"0.6492800546399922"
      },
      {
         "id":"20155",
         "cluster":"5",
         "title":"Marcus Aurelius",
         "relatedness":"0.6110878245795968"
      },
      {
         "id":"20875",
         "cluster":"5",
         "title":"Melancholia",
         "relatedness":"0.6471309252177174"
      },
      {
         "id":"2590334",
         "cluster":"5",
         "title":"Metaphysics (Aristotle)",
         "relatedness":"0.756208794755928"
      },
      {
         "id":"44307",
         "cluster":"5",
         "title":"Michel de Montaigne",
         "relatedness":"0.6296258368200651"
      },
      {
         "id":"577035",
         "cluster":"5",
         "title":"Nondualism",
         "relatedness":"0.6848786618247829"
      },
      {
         "id":"22261",
         "cluster":"5",
         "title":"Ontology",
         "relatedness":"0.729483796150692"
      },
      {
         "id":"23590",
         "cluster":"5",
         "title":"Pantheism",
         "relatedness":"0.7215459016429353"
      },
      {
         "id":"210191",
         "cluster":"5",
         "title":"Philo",
         "relatedness":"0.6958798885844835"
      },
      {
         "id":"655002",
         "cluster":"5",
         "title":"Philosophy of space and time",
         "relatedness":"0.7143761899280634"
      },
      {
         "id":"2420319",
         "cluster":"5",
         "title":"Platonic Academy",
         "relatedness":"0.6756528656764051"
      },
      {
         "id":"24269",
         "cluster":"5",
         "title":"Process philosophy",
         "relatedness":"0.7340728712118477"
      },
      {
         "id":"59855",
         "cluster":"5",
         "title":"Rhea (mythology)",
         "relatedness":"0.6252714328033327"
      },
      {
         "id":"25453",
         "cluster":"5",
         "title":"Rheology",
         "relatedness":"0.5933631412923962"
      },
      {
         "id":"80003",
         "cluster":"5",
         "title":"Satrap",
         "relatedness":"0.5794599737402231"
      },
      {
         "id":"19342760",
         "cluster":"5",
         "title":"Seven Wonders of the Ancient World",
         "relatedness":"0.594861497783887"
      },
      {
         "id":"80442",
         "cluster":"5",
         "title":"Simplicius of Cilicia",
         "relatedness":"0.7260193300351685"
      },
      {
         "id":"78402",
         "cluster":"5",
         "title":"Stobaeus",
         "relatedness":"0.6761387255775845"
      },
      {
         "id":"19224834",
         "cluster":"5",
         "title":"Stoicism",
         "relatedness":"0.7143004007555502"
      },
      {
         "id":"27900915",
         "cluster":"5",
         "title":"Temple of Artemis",
         "relatedness":"0.6400175335656635"
      },
      {
         "id":"1219302",
         "cluster":"5",
         "title":"Timon of Phlius",
         "relatedness":"0.7226397557353625"
      },
      {
         "id":"30660537",
         "cluster":"5",
         "title":"Triple Canopy (online magazine)",
         "relatedness":"0.5983415949818349"
      },
      {
         "id":"10325000",
         "cluster":"5",
         "title":"Unity of opposites",
         "relatedness":"0.7272713088307319"
      },
      {
         "id":"31880",
         "cluster":"5",
         "title":"Universe",
         "relatedness":"0.6404785918439747"
      },
      {
         "id":"34398",
         "cluster":"5",
         "title":"Zeus",
         "relatedness":"0.5610026831212961"
      },
      {
         "id":"507380",
         "cluster":"5",
         "title":"Ancient Agora of Athens",
         "relatedness":"0.7629600429397371"
      },
      {
         "id":"249552",
         "cluster":"5",
         "title":"Antigonus II Gonatas",
         "relatedness":"0.7415423567888606"
      },
      {
         "id":"1887751",
         "cluster":"5",
         "title":"Aristo of Chios",
         "relatedness":"0.8084415255457517"
      },
      {
         "id":"37143",
         "cluster":"5",
         "title":"Chrysippus",
         "relatedness":"0.8905998768362561"
      },
      {
         "id":"80039",
         "cluster":"5",
         "title":"Crates of Thebes",
         "relatedness":"0.8769513551368588"
      },
      {
         "id":"19187131",
         "cluster":"5",
         "title":"Cynicism",
         "relatedness":"0.7946276888505094"
      },
      {
         "id":"469691",
         "cluster":"5",
         "title":"Destiny",
         "relatedness":"0.6644017275731001"
      },
      {
         "id":"2437676",
         "cluster":"5",
         "title":"Diodorus Cronus",
         "relatedness":"0.8468839616567588"
      },
      {
         "id":"8363",
         "cluster":"5",
         "title":"Divinity",
         "relatedness":"0.6369566933051614"
      },
      {
         "id":"10406",
         "cluster":"5",
         "title":"Emotion",
         "relatedness":"0.5503500735626715"
      },
      {
         "id":"9897",
         "cluster":"5",
         "title":"Evil",
         "relatedness":"0.5545702621279714"
      },
      {
         "id":"4157971",
         "cluster":"5",
         "title":"Goodness",
         "relatedness":"0.6685053818366195"
      },
      {
         "id":"12569",
         "cluster":"5",
         "title":"Grammar",
         "relatedness":"0.5076945802150157"
      },
      {
         "id":"243391",
         "cluster":"5",
         "title":"Knowledge",
         "relatedness":"0.5663574999876313"
      },
      {
         "id":"287852",
         "cluster":"5",
         "title":"Larnaca",
         "relatedness":"0.7082035784211762"
      },
      {
         "id":"174455",
         "cluster":"5",
         "title":"Lentil",
         "relatedness":"0.6280298763706038"
      },
      {
         "id":"3729225",
         "cluster":"5",
         "title":"Logic",
         "relatedness":"0.615078751736452"
      },
      {
         "id":"42012",
         "cluster":"5",
         "title":"Macedonia (ancient kingdom)",
         "relatedness":"0.6113977367633239"
      },
      {
         "id":"1219340",
         "cluster":"5",
         "title":"Megarian school",
         "relatedness":"0.8329221924326833"
      },
      {
         "id":"21830",
         "cluster":"5",
         "title":"Nature",
         "relatedness":"0.6148108390389497"
      },
      {
         "id":"78968",
         "cluster":"5",
         "title":"Niobe",
         "relatedness":"0.6327842066146039"
      },
      {
         "id":"419686",
         "cluster":"5",
         "title":"Pedagogy",
         "relatedness":"0.520627021892176"
      },
      {
         "id":"25140",
         "cluster":"5",
         "title":"Perception",
         "relatedness":"0.547908602027182"
      },
      {
         "id":"14125745",
         "cluster":"5",
         "title":"Philo the Dialectician",
         "relatedness":"0.8243732704627958"
      },
      {
         "id":"2221011",
         "cluster":"5",
         "title":"Platonism",
         "relatedness":"0.6980816075426228"
      },
      {
         "id":"9734298",
         "cluster":"5",
         "title":"Polemon (scholarch)",
         "relatedness":"0.7856466655207813"
      },
      {
         "id":"17832909",
         "cluster":"5",
         "title":"Scholarch",
         "relatedness":"0.8061062961994516"
      },
      {
         "id":"1219317",
         "cluster":"5",
         "title":"Stilpo",
         "relatedness":"0.8433075749554192"
      },
      {
         "id":"208583",
         "cluster":"5",
         "title":"Stoa",
         "relatedness":"0.7337695199036978"
      },
      {
         "id":"1462051",
         "cluster":"5",
         "title":"Stoa Poikile",
         "relatedness":"0.7825460213116198"
      },
      {
         "id":"30365",
         "cluster":"5",
         "title":"Taoism",
         "relatedness":"0.5636457527381235"
      },
      {
         "id":"37080",
         "cluster":"5",
         "title":"Thought",
         "relatedness":"0.5931268585805346"
      },
      {
         "id":"49901",
         "cluster":"5",
         "title":"Virtue",
         "relatedness":"0.7149640194822738"
      },
      {
         "id":"171850",
         "cluster":"5",
         "title":"Xenocrates",
         "relatedness":"0.8104209407476685"
      },
      {
         "id":"0",
         "root":true,
         "type": "philosopher",
         "title":"Pythagoras"
      },
      {
         "id":"1",
         "root":true,
         "type": "philosopher",
         "title":"Heraclitus"
      },
      {
         "id":"2",
         "root":true,
         "type": "philosopher",
         "title":"Gorgias"
      },
      {
         "id":"3",
         "root":true,
         "type": "philosopher",
         "title":"Zeno"
      },
      {
         "id":"4",
         "root":true,
         "type": "philosopher",
         "title":"Democritus"
      }
   ],
   "edges":[
      {
         "source":"0",
         "target":"2110950",
         "relatedness":"0.6416031476416721"
      },
      {
         "source":"0",
         "target":"379264",
         "relatedness":"0.6605042722871506"
      },
      {
         "source":"0",
         "target":"842",
         "relatedness":"0.5738613572915624"
      },
      {
         "source":"0",
         "target":"573",
         "relatedness":"0.6613786186196584"
      },
      {
         "source":"0",
         "target":"1168",
         "relatedness":"0.7995214766975139"
      },
      {
         "source":"0",
         "target":"66540",
         "relatedness":"0.6247677116583654"
      },
      {
         "source":"0",
         "target":"4831143",
         "relatedness":"0.6484342496247335"
      },
      {
         "source":"0",
         "target":"171171",
         "relatedness":"0.7615431029572908"
      },
      {
         "source":"1",
         "target":"171171",
         "relatedness":"0.7615431029572908"
      },
      {
         "source":"3",
         "target":"171171",
         "relatedness":"0.7615431029572908"
      },
      {
         "source":"0",
         "target":"594",
         "relatedness":"0.6062473786781528"
      },
      {
         "source":"0",
         "target":"67161",
         "relatedness":"0.6918429504353061"
      },
      {
         "source":"0",
         "target":"243369",
         "relatedness":"0.6708810679360462"
      },
      {
         "source":"0",
         "target":"252342",
         "relatedness":"0.6660273664998236"
      },
      {
         "source":"0",
         "target":"308",
         "relatedness":"0.6765244120849302"
      },
      {
         "source":"1",
         "target":"308",
         "relatedness":"0.6765244120849302"
      },
      {
         "source":"2",
         "target":"308",
         "relatedness":"0.6765244120849302"
      },
      {
         "source":"0",
         "target":"98921",
         "relatedness":"0.7383862669303789"
      },
      {
         "source":"0",
         "target":"83484",
         "relatedness":"0.568999701315425"
      },
      {
         "source":"4",
         "target":"83484",
         "relatedness":"0.568999701315425"
      },
      {
         "source":"0",
         "target":"20609622",
         "relatedness":"0.6210384792425094"
      },
      {
         "source":"1",
         "target":"20609622",
         "relatedness":"0.6210384792425094"
      },
      {
         "source":"0",
         "target":"3861353",
         "relatedness":"0.7175172379500785"
      },
      {
         "source":"0",
         "target":"4487",
         "relatedness":"0.5158566411616861"
      },
      {
         "source":"0",
         "target":"4163",
         "relatedness":"0.5841509367313082"
      },
      {
         "source":"1",
         "target":"4163",
         "relatedness":"0.5841509367313082"
      },
      {
         "source":"0",
         "target":"1067391",
         "relatedness":"0.6791325896923349"
      },
      {
         "source":"0",
         "target":"356705",
         "relatedness":"0.5284880738840145"
      },
      {
         "source":"0",
         "target":"6599",
         "relatedness":"0.614322785683099"
      },
      {
         "source":"0",
         "target":"6046",
         "relatedness":"0.6299126760904048"
      },
      {
         "source":"3",
         "target":"6046",
         "relatedness":"0.6299126760904048"
      },
      {
         "source":"4",
         "target":"6046",
         "relatedness":"0.6299126760904048"
      },
      {
         "source":"0",
         "target":"252905",
         "relatedness":"0.6051503835137271"
      },
      {
         "source":"0",
         "target":"6591",
         "relatedness":"0.5231866407403841"
      },
      {
         "source":"0",
         "target":"81177",
         "relatedness":"0.6964250302913964"
      },
      {
         "source":"0",
         "target":"350137",
         "relatedness":"0.5753801798232456"
      },
      {
         "source":"0",
         "target":"79077",
         "relatedness":"0.6435269156277214"
      },
      {
         "source":"0",
         "target":"47724",
         "relatedness":"0.6495375581669776"
      },
      {
         "source":"0",
         "target":"8691",
         "relatedness":"0.6324115752228379"
      },
      {
         "source":"0",
         "target":"8632",
         "relatedness":"0.5538260740913374"
      },
      {
         "source":"0",
         "target":"10109",
         "relatedness":"0.645406897775751"
      },
      {
         "source":"0",
         "target":"9258",
         "relatedness":"0.5443786795852789"
      },
      {
         "source":"4",
         "target":"9258",
         "relatedness":"0.5443786795852789"
      },
      {
         "source":"0",
         "target":"37004",
         "relatedness":"0.6827205739420514"
      },
      {
         "source":"0",
         "target":"4385475",
         "relatedness":"0.6777685746941282"
      },
      {
         "source":"0",
         "target":"539937",
         "relatedness":"0.5331506310600507"
      },
      {
         "source":"0",
         "target":"97052",
         "relatedness":"0.5379768102364013"
      },
      {
         "source":"0",
         "target":"171867",
         "relatedness":"0.7366519985499261"
      },
      {
         "source":"0",
         "target":"68928",
         "relatedness":"0.7166498057452753"
      },
      {
         "source":"0",
         "target":"13574",
         "relatedness":"0.6594208578939411"
      },
      {
         "source":"0",
         "target":"732860",
         "relatedness":"0.7621759599773158"
      },
      {
         "source":"0",
         "target":"1848052",
         "relatedness":"0.6827077143364553"
      },
      {
         "source":"0",
         "target":"340504",
         "relatedness":"0.6794881286804026"
      },
      {
         "source":"1",
         "target":"340504",
         "relatedness":"0.6794881286804026"
      },
      {
         "source":"0",
         "target":"168260",
         "relatedness":"0.624950527834167"
      },
      {
         "source":"2",
         "target":"168260",
         "relatedness":"0.624950527834167"
      },
      {
         "source":"0",
         "target":"674577",
         "relatedness":"0.6510341961367369"
      },
      {
         "source":"0",
         "target":"2002484",
         "relatedness":"0.5711977743099564"
      },
      {
         "source":"0",
         "target":"61963",
         "relatedness":"0.6670074377328987"
      },
      {
         "source":"0",
         "target":"207217",
         "relatedness":"0.6519296147980969"
      },
      {
         "source":"0",
         "target":"45333",
         "relatedness":"0.6927957847873181"
      },
      {
         "source":"0",
         "target":"18902",
         "relatedness":"0.5372296042594061"
      },
      {
         "source":"0",
         "target":"18831",
         "relatedness":"0.5012457157834864"
      },
      {
         "source":"0",
         "target":"2062173",
         "relatedness":"0.6694527508235071"
      },
      {
         "source":"0",
         "target":"53141",
         "relatedness":"0.6600613101555224"
      },
      {
         "source":"0",
         "target":"64222",
         "relatedness":"0.6776053890095273"
      },
      {
         "source":"0",
         "target":"492229",
         "relatedness":"0.6325911637816397"
      },
      {
         "source":"0",
         "target":"1977435",
         "relatedness":"0.5927990684797471"
      },
      {
         "source":"0",
         "target":"4116363",
         "relatedness":"0.6449424799860168"
      },
      {
         "source":"0",
         "target":"318648",
         "relatedness":"0.7257807999803645"
      },
      {
         "source":"0",
         "target":"29174999",
         "relatedness":"0.5893213144543406"
      },
      {
         "source":"3",
         "target":"29174999",
         "relatedness":"0.5893213144543406"
      },
      {
         "source":"0",
         "target":"382251",
         "relatedness":"0.7049986071478864"
      },
      {
         "source":"0",
         "target":"23385833",
         "relatedness":"0.7360789831523709"
      },
      {
         "source":"3",
         "target":"23385833",
         "relatedness":"0.7360789831523709"
      },
      {
         "source":"0",
         "target":"1128528",
         "relatedness":"0.7264651325771045"
      },
      {
         "source":"0",
         "target":"21137",
         "relatedness":"0.7001050005340894"
      },
      {
         "source":"0",
         "target":"1403568",
         "relatedness":"0.6810517697609638"
      },
      {
         "source":"0",
         "target":"841452",
         "relatedness":"0.7512803523835881"
      },
      {
         "source":"0",
         "target":"13692155",
         "relatedness":"0.5541665841660619"
      },
      {
         "source":"1",
         "target":"13692155",
         "relatedness":"0.5541665841660619"
      },
      {
         "source":"0",
         "target":"4676511",
         "relatedness":"0.5508728958676994"
      },
      {
         "source":"0",
         "target":"24202",
         "relatedness":"0.5738613572915624"
      },
      {
         "source":"4",
         "target":"24202",
         "relatedness":"0.5738613572915624"
      },
      {
         "source":"0",
         "target":"22954",
         "relatedness":"0.7205876164166645"
      },
      {
         "source":"1",
         "target":"22954",
         "relatedness":"0.7205876164166645"
      },
      {
         "source":"2",
         "target":"22954",
         "relatedness":"0.7205876164166645"
      },
      {
         "source":"3",
         "target":"22954",
         "relatedness":"0.7205876164166645"
      },
      {
         "source":"4",
         "target":"22954",
         "relatedness":"0.7205876164166645"
      },
      {
         "source":"0",
         "target":"24517",
         "relatedness":"0.6511673556413374"
      },
      {
         "source":"3",
         "target":"24517",
         "relatedness":"0.6511673556413374"
      },
      {
         "source":"0",
         "target":"455361",
         "relatedness":"0.6898562810950611"
      },
      {
         "source":"0",
         "target":"794399",
         "relatedness":"0.7526719820332808"
      },
      {
         "source":"0",
         "target":"30340",
         "relatedness":"0.7700554439389743"
      },
      {
         "source":"1",
         "target":"30340",
         "relatedness":"0.7700554439389743"
      },
      {
         "source":"2",
         "target":"30340",
         "relatedness":"0.7700554439389743"
      },
      {
         "source":"3",
         "target":"30340",
         "relatedness":"0.7700554439389743"
      },
      {
         "source":"0",
         "target":"177721",
         "relatedness":"0.6682716690236411"
      },
      {
         "source":"0",
         "target":"26513034",
         "relatedness":"0.7295570914667924"
      },
      {
         "source":"0",
         "target":"291170",
         "relatedness":"0.8227579605206381"
      },
      {
         "source":"0",
         "target":"53258",
         "relatedness":"0.6562083848651177"
      },
      {
         "source":"0",
         "target":"243824",
         "relatedness":"0.5155449098889353"
      },
      {
         "source":"0",
         "target":"25806",
         "relatedness":"0.6244620056302578"
      },
      {
         "source":"0",
         "target":"49972",
         "relatedness":"0.6798686079289702"
      },
      {
         "source":"0",
         "target":"46754",
         "relatedness":"0.6649586040116859"
      },
      {
         "source":"0",
         "target":"3333684",
         "relatedness":"0.6880855662192364"
      },
      {
         "source":"0",
         "target":"26700",
         "relatedness":"0.509788546277322"
      },
      {
         "source":"0",
         "target":"28297",
         "relatedness":"0.5983229512557059"
      },
      {
         "source":"4",
         "target":"28297",
         "relatedness":"0.5983229512557059"
      },
      {
         "source":"0",
         "target":"36487",
         "relatedness":"0.598760589249347"
      },
      {
         "source":"2",
         "target":"36487",
         "relatedness":"0.598760589249347"
      },
      {
         "source":"0",
         "target":"191464",
         "relatedness":"0.6557616028474984"
      },
      {
         "source":"0",
         "target":"56148",
         "relatedness":"0.5894378595026769"
      },
      {
         "source":"0",
         "target":"1570530",
         "relatedness":"0.7009795857133676"
      },
      {
         "source":"0",
         "target":"30072",
         "relatedness":"0.810671065693759"
      },
      {
         "source":"0",
         "target":"1607411",
         "relatedness":"0.6680877199530644"
      },
      {
         "source":"0",
         "target":"936952",
         "relatedness":"0.681064902496793"
      },
      {
         "source":"0",
         "target":"69035",
         "relatedness":"0.6278082788653148"
      },
      {
         "source":"0",
         "target":"30058",
         "relatedness":"0.5857261200121455"
      },
      {
         "source":"2",
         "target":"30058",
         "relatedness":"0.5857261200121455"
      },
      {
         "source":"0",
         "target":"153945",
         "relatedness":"0.5453923314775599"
      },
      {
         "source":"0",
         "target":"13704154",
         "relatedness":"0.6569359968684766"
      },
      {
         "source":"0",
         "target":"223339",
         "relatedness":"0.755977410266038"
      },
      {
         "source":"3",
         "target":"223339",
         "relatedness":"0.755977410266038"
      },
      {
         "source":"0",
         "target":"id",
         "relatedness":"relatedness"
      },
      {
         "source":"1",
         "target":"id",
         "relatedness":"relatedness"
      },
      {
         "source":"2",
         "target":"id",
         "relatedness":"relatedness"
      },
      {
         "source":"3",
         "target":"id",
         "relatedness":"relatedness"
      },
      {
         "source":"4",
         "target":"id",
         "relatedness":"relatedness"
      },
      {
         "source":"1",
         "target":"2685",
         "relatedness":"0.7915199823620525"
      },
      {
         "source":"1",
         "target":"862898",
         "relatedness":"0.6672581874322139"
      },
      {
         "source":"1",
         "target":"1737",
         "relatedness":"0.8363200988089976"
      },
      {
         "source":"1",
         "target":"470031",
         "relatedness":"0.5802197895089702"
      },
      {
         "source":"1",
         "target":"620653",
         "relatedness":"0.6625294609566587"
      },
      {
         "source":"1",
         "target":"1216",
         "relatedness":"0.5078126607081992"
      },
      {
         "source":"3",
         "target":"1216",
         "relatedness":"0.5078126607081992"
      },
      {
         "source":"4",
         "target":"1216",
         "relatedness":"0.5078126607081992"
      },
      {
         "source":"1",
         "target":"902",
         "relatedness":"0.6631931497061192"
      },
      {
         "source":"1",
         "target":"2844",
         "relatedness":"0.7924866329506831"
      },
      {
         "source":"1",
         "target":"5756554",
         "relatedness":"0.8899409781472871"
      },
      {
         "source":"1",
         "target":"15667214",
         "relatedness":"0.5689183157309515"
      },
      {
         "source":"1",
         "target":"692207",
         "relatedness":"0.6024639997422234"
      },
      {
         "source":"1",
         "target":"547420",
         "relatedness":"0.5253940971009647"
      },
      {
         "source":"1",
         "target":"782427",
         "relatedness":"0.577519145452525"
      },
      {
         "source":"1",
         "target":"2582448",
         "relatedness":"0.7188670825324923"
      },
      {
         "source":"1",
         "target":"859283",
         "relatedness":"0.5454125540305599"
      },
      {
         "source":"1",
         "target":"272167",
         "relatedness":"0.7521544450468121"
      },
      {
         "source":"1",
         "target":"2398094",
         "relatedness":"0.7144218801192832"
      },
      {
         "source":"1",
         "target":"99425",
         "relatedness":"0.5731696581603622"
      },
      {
         "source":"1",
         "target":"1180105",
         "relatedness":"0.5738144004878518"
      },
      {
         "source":"1",
         "target":"10073",
         "relatedness":"0.8671574398094801"
      },
      {
         "source":"1",
         "target":"724601",
         "relatedness":"0.6615014853533052"
      },
      {
         "source":"3",
         "target":"724601",
         "relatedness":"0.6615014853533052"
      },
      {
         "source":"1",
         "target":"8347",
         "relatedness":"0.5795550761959087"
      },
      {
         "source":"1",
         "target":"6266257",
         "relatedness":"0.7284296996928117"
      },
      {
         "source":"3",
         "target":"6266257",
         "relatedness":"0.7284296996928117"
      },
      {
         "source":"1",
         "target":"13486",
         "relatedness":"0.7220058783467134"
      },
      {
         "source":"1",
         "target":"14627",
         "relatedness":"0.6491770280334401"
      },
      {
         "source":"1",
         "target":"4147143",
         "relatedness":"0.7284296996928117"
      },
      {
         "source":"3",
         "target":"4147143",
         "relatedness":"0.7284296996928117"
      },
      {
         "source":"1",
         "target":"44112",
         "relatedness":"0.7568762979727915"
      },
      {
         "source":"1",
         "target":"561941",
         "relatedness":"0.7603165276457737"
      },
      {
         "source":"1",
         "target":"17924",
         "relatedness":"0.8829555858752104"
      },
      {
         "source":"1",
         "target":"690316",
         "relatedness":"0.5975419071423698"
      },
      {
         "source":"1",
         "target":"1738950",
         "relatedness":"0.7003043365950324"
      },
      {
         "source":"4",
         "target":"1738950",
         "relatedness":"0.7003043365950324"
      },
      {
         "source":"1",
         "target":"37145",
         "relatedness":"0.8145701825401164"
      },
      {
         "source":"1",
         "target":"19376",
         "relatedness":"0.6866479038427777"
      },
      {
         "source":"1",
         "target":"395107",
         "relatedness":"0.7408196379846586"
      },
      {
         "source":"1",
         "target":"582988",
         "relatedness":"0.5533371443914934"
      },
      {
         "source":"1",
         "target":"1760214",
         "relatedness":"0.5793300030000328"
      },
      {
         "source":"1",
         "target":"332902",
         "relatedness":"0.6728922500496926"
      },
      {
         "source":"3",
         "target":"332902",
         "relatedness":"0.6728922500496926"
      },
      {
         "source":"1",
         "target":"2281137",
         "relatedness":"0.7340019871217529"
      },
      {
         "source":"1",
         "target":"23575",
         "relatedness":"0.8130080648795733"
      },
      {
         "source":"2",
         "target":"23575",
         "relatedness":"0.8130080648795733"
      },
      {
         "source":"1",
         "target":"248171",
         "relatedness":"0.5922792822022505"
      },
      {
         "source":"1",
         "target":"87868",
         "relatedness":"0.7278788233005739"
      },
      {
         "source":"1",
         "target":"283007",
         "relatedness":"0.5847686376949165"
      },
      {
         "source":"1",
         "target":"23704",
         "relatedness":"0.5172926266161442"
      },
      {
         "source":"1",
         "target":"25532",
         "relatedness":"0.515728245805086"
      },
      {
         "source":"3",
         "target":"25532",
         "relatedness":"0.515728245805086"
      },
      {
         "source":"1",
         "target":"105309",
         "relatedness":"0.5354101143339662"
      },
      {
         "source":"1",
         "target":"177582",
         "relatedness":"0.7634691509813191"
      },
      {
         "source":"2",
         "target":"177582",
         "relatedness":"0.7634691509813191"
      },
      {
         "source":"1",
         "target":"25664190",
         "relatedness":"0.7238432739555936"
      },
      {
         "source":"4",
         "target":"25664190",
         "relatedness":"0.7238432739555936"
      },
      {
         "source":"1",
         "target":"357356",
         "relatedness":"0.6023880009322542"
      },
      {
         "source":"1",
         "target":"52121",
         "relatedness":"0.5580347699731832"
      },
      {
         "source":"3",
         "target":"52121",
         "relatedness":"0.5580347699731832"
      },
      {
         "source":"1",
         "target":"2794118",
         "relatedness":"0.6881858482908192"
      },
      {
         "source":"1",
         "target":"98409",
         "relatedness":"0.7591161541331883"
      },
      {
         "source":"3",
         "target":"98409",
         "relatedness":"0.7591161541331883"
      },
      {
         "source":"1",
         "target":"36857",
         "relatedness":"0.5832624958774828"
      },
      {
         "source":"1",
         "target":"2068728",
         "relatedness":"0.7106126916095001"
      },
      {
         "source":"1",
         "target":"21391464",
         "relatedness":"0.5996792439881455"
      },
      {
         "source":"2",
         "target":"21391464",
         "relatedness":"0.5996792439881455"
      },
      {
         "source":"3",
         "target":"21391464",
         "relatedness":"0.5996792439881455"
      },
      {
         "source":"1",
         "target":"307366",
         "relatedness":"0.7492042443743117"
      },
      {
         "source":"1",
         "target":"32498",
         "relatedness":"0.5463482078384988"
      },
      {
         "source":"1",
         "target":"46289",
         "relatedness":"0.6484569132222768"
      },
      {
         "source":"1",
         "target":"143331",
         "relatedness":"0.8010760542113754"
      },
      {
         "source":"2",
         "target":"1544",
         "relatedness":"0.6218641803454983"
      },
      {
         "source":"2",
         "target":"1549",
         "relatedness":"0.7732150306168516"
      },
      {
         "source":"2",
         "target":"61322",
         "relatedness":"0.7469739013537938"
      },
      {
         "source":"2",
         "target":"98367",
         "relatedness":"0.8090638611821409"
      },
      {
         "source":"2",
         "target":"1174",
         "relatedness":"0.5165024011984077"
      },
      {
         "source":"2",
         "target":"85436",
         "relatedness":"0.577023799381168"
      },
      {
         "source":"2",
         "target":"302613",
         "relatedness":"0.5749588030816335"
      },
      {
         "source":"2",
         "target":"296018",
         "relatedness":"0.7856315114005384"
      },
      {
         "source":"2",
         "target":"7951",
         "relatedness":"0.6106862216427451"
      },
      {
         "source":"2",
         "target":"6266436",
         "relatedness":"0.7038915662526177"
      },
      {
         "source":"3",
         "target":"6266436",
         "relatedness":"0.7038915662526177"
      },
      {
         "source":"2",
         "target":"1250251",
         "relatedness":"0.6981192401873191"
      },
      {
         "source":"2",
         "target":"591116",
         "relatedness":"0.8193247550367888"
      },
      {
         "source":"2",
         "target":"9553",
         "relatedness":"0.7858509006703615"
      },
      {
         "source":"2",
         "target":"4202524",
         "relatedness":"0.8025783446893925"
      },
      {
         "source":"2",
         "target":"1178825",
         "relatedness":"0.836068462949139"
      },
      {
         "source":"2",
         "target":"63444",
         "relatedness":"0.6199435232883228"
      },
      {
         "source":"2",
         "target":"13208",
         "relatedness":"0.5495862731885246"
      },
      {
         "source":"2",
         "target":"18490",
         "relatedness":"0.6394505684590723"
      },
      {
         "source":"2",
         "target":"26630411",
         "relatedness":"0.7418692485435604"
      },
      {
         "source":"2",
         "target":"154997",
         "relatedness":"0.732410178838381"
      },
      {
         "source":"2",
         "target":"46299",
         "relatedness":"0.6343459156488389"
      },
      {
         "source":"2",
         "target":"10916048",
         "relatedness":"0.7833364103130014"
      },
      {
         "source":"2",
         "target":"21663",
         "relatedness":"0.551626002233395"
      },
      {
         "source":"2",
         "target":"60686",
         "relatedness":"0.6781865482126846"
      },
      {
         "source":"2",
         "target":"22537",
         "relatedness":"0.5887255549579715"
      },
      {
         "source":"2",
         "target":"36812",
         "relatedness":"0.7262321223156234"
      },
      {
         "source":"2",
         "target":"80271",
         "relatedness":"0.7726659561352092"
      },
      {
         "source":"2",
         "target":"24086",
         "relatedness":"0.8730601511982513"
      },
      {
         "source":"2",
         "target":"25447",
         "relatedness":"0.6732003655116786"
      },
      {
         "source":"4",
         "target":"25447",
         "relatedness":"0.6732003655116786"
      },
      {
         "source":"2",
         "target":"23939752",
         "relatedness":"0.8060564145965303"
      },
      {
         "source":"2",
         "target":"9393762",
         "relatedness":"0.6809660452136008"
      },
      {
         "source":"2",
         "target":"78815",
         "relatedness":"0.673738593380198"
      },
      {
         "source":"2",
         "target":"28441",
         "relatedness":"0.6184777230280556"
      },
      {
         "source":"2",
         "target":"74673",
         "relatedness":"0.640507469681953"
      },
      {
         "source":"2",
         "target":"55804",
         "relatedness":"0.5588358111125056"
      },
      {
         "source":"2",
         "target":"30864",
         "relatedness":"0.6730726927079262"
      },
      {
         "source":"2",
         "target":"9735736",
         "relatedness":"0.6824539359205452"
      },
      {
         "source":"3",
         "target":"30927438",
         "relatedness":"0.543197042788502"
      },
      {
         "source":"3",
         "target":"148363",
         "relatedness":"0.5413273471827904"
      },
      {
         "source":"3",
         "target":"256799",
         "relatedness":"0.6647366402117068"
      },
      {
         "source":"3",
         "target":"78336",
         "relatedness":"0.7112593744264282"
      },
      {
         "source":"3",
         "target":"2905",
         "relatedness":"0.5554549016717987"
      },
      {
         "source":"3",
         "target":"2266434",
         "relatedness":"0.6331611647819314"
      },
      {
         "source":"3",
         "target":"219168",
         "relatedness":"0.5812838039355139"
      },
      {
         "source":"3",
         "target":"171297",
         "relatedness":"0.7253956223012543"
      },
      {
         "source":"4",
         "target":"171297",
         "relatedness":"0.7253956223012543"
      },
      {
         "source":"3",
         "target":"7342",
         "relatedness":"0.6626448798037462"
      },
      {
         "source":"3",
         "target":"38737",
         "relatedness":"0.7268893326091334"
      },
      {
         "source":"3",
         "target":"6166042",
         "relatedness":"0.7388385040205425"
      },
      {
         "source":"3",
         "target":"2211169",
         "relatedness":"0.7209623015389626"
      },
      {
         "source":"3",
         "target":"52813",
         "relatedness":"0.7120200038844138"
      },
      {
         "source":"4",
         "target":"52813",
         "relatedness":"0.7120200038844138"
      },
      {
         "source":"3",
         "target":"724627",
         "relatedness":"0.7321454703797035"
      },
      {
         "source":"3",
         "target":"219366",
         "relatedness":"0.6656173629779143"
      },
      {
         "source":"3",
         "target":"8135",
         "relatedness":"0.7196533347296719"
      },
      {
         "source":"3",
         "target":"9843",
         "relatedness":"0.6783962130354709"
      },
      {
         "source":"3",
         "target":"2877300",
         "relatedness":"0.5460279871613714"
      },
      {
         "source":"3",
         "target":"12598",
         "relatedness":"0.6981716175516036"
      },
      {
         "source":"3",
         "target":"455379",
         "relatedness":"0.6463607647606976"
      },
      {
         "source":"4",
         "target":"455379",
         "relatedness":"0.6463607647606976"
      },
      {
         "source":"3",
         "target":"20611083",
         "relatedness":"0.5110881525036353"
      },
      {
         "source":"3",
         "target":"13700",
         "relatedness":"0.6773813738076832"
      },
      {
         "source":"3",
         "target":"724911",
         "relatedness":"0.6425967224467999"
      },
      {
         "source":"3",
         "target":"13633",
         "relatedness":"0.6101406270550802"
      },
      {
         "source":"3",
         "target":"46401",
         "relatedness":"0.7113329613265493"
      },
      {
         "source":"3",
         "target":"2529261",
         "relatedness":"0.71963272007617"
      },
      {
         "source":"3",
         "target":"7499245",
         "relatedness":"0.6449026837648028"
      },
      {
         "source":"3",
         "target":"3125551",
         "relatedness":"0.6073045726350639"
      },
      {
         "source":"3",
         "target":"1023023",
         "relatedness":"0.5579118381283068"
      },
      {
         "source":"3",
         "target":"319762",
         "relatedness":"0.7816834469166378"
      },
      {
         "source":"4",
         "target":"319762",
         "relatedness":"0.7816834469166378"
      },
      {
         "source":"3",
         "target":"165457",
         "relatedness":"0.6492800546399922"
      },
      {
         "source":"3",
         "target":"20155",
         "relatedness":"0.6110878245795968"
      },
      {
         "source":"3",
         "target":"20875",
         "relatedness":"0.6471309252177174"
      },
      {
         "source":"3",
         "target":"2590334",
         "relatedness":"0.756208794755928"
      },
      {
         "source":"3",
         "target":"44307",
         "relatedness":"0.6296258368200651"
      },
      {
         "source":"3",
         "target":"577035",
         "relatedness":"0.6848786618247829"
      },
      {
         "source":"3",
         "target":"22261",
         "relatedness":"0.729483796150692"
      },
      {
         "source":"3",
         "target":"23590",
         "relatedness":"0.7215459016429353"
      },
      {
         "source":"4",
         "target":"23590",
         "relatedness":"0.7215459016429353"
      },
      {
         "source":"3",
         "target":"210191",
         "relatedness":"0.6958798885844835"
      },
      {
         "source":"3",
         "target":"655002",
         "relatedness":"0.7143761899280634"
      },
      {
         "source":"3",
         "target":"2420319",
         "relatedness":"0.6756528656764051"
      },
      {
         "source":"4",
         "target":"2420319",
         "relatedness":"0.6756528656764051"
      },
      {
         "source":"3",
         "target":"24269",
         "relatedness":"0.7340728712118477"
      },
      {
         "source":"3",
         "target":"59855",
         "relatedness":"0.6252714328033327"
      },
      {
         "source":"3",
         "target":"25453",
         "relatedness":"0.5933631412923962"
      },
      {
         "source":"3",
         "target":"80003",
         "relatedness":"0.5794599737402231"
      },
      {
         "source":"3",
         "target":"19342760",
         "relatedness":"0.594861497783887"
      },
      {
         "source":"3",
         "target":"80442",
         "relatedness":"0.7260193300351685"
      },
      {
         "source":"3",
         "target":"78402",
         "relatedness":"0.6761387255775845"
      },
      {
         "source":"3",
         "target":"19224834",
         "relatedness":"0.7143004007555502"
      },
      {
         "source":"4",
         "target":"19224834",
         "relatedness":"0.7143004007555502"
      },
      {
         "source":"3",
         "target":"27900915",
         "relatedness":"0.6400175335656635"
      },
      {
         "source":"3",
         "target":"1219302",
         "relatedness":"0.7226397557353625"
      },
      {
         "source":"3",
         "target":"30660537",
         "relatedness":"0.5983415949818349"
      },
      {
         "source":"3",
         "target":"10325000",
         "relatedness":"0.7272713088307319"
      },
      {
         "source":"3",
         "target":"31880",
         "relatedness":"0.6404785918439747"
      },
      {
         "source":"4",
         "target":"31880",
         "relatedness":"0.6404785918439747"
      },
      {
         "source":"3",
         "target":"34398",
         "relatedness":"0.5610026831212961"
      },
      {
         "source":"4",
         "target":"507380",
         "relatedness":"0.7629600429397371"
      },
      {
         "source":"4",
         "target":"249552",
         "relatedness":"0.7415423567888606"
      },
      {
         "source":"4",
         "target":"1887751",
         "relatedness":"0.8084415255457517"
      },
      {
         "source":"4",
         "target":"37143",
         "relatedness":"0.8905998768362561"
      },
      {
         "source":"4",
         "target":"80039",
         "relatedness":"0.8769513551368588"
      },
      {
         "source":"4",
         "target":"19187131",
         "relatedness":"0.7946276888505094"
      },
      {
         "source":"4",
         "target":"469691",
         "relatedness":"0.6644017275731001"
      },
      {
         "source":"4",
         "target":"2437676",
         "relatedness":"0.8468839616567588"
      },
      {
         "source":"4",
         "target":"8363",
         "relatedness":"0.6369566933051614"
      },
      {
         "source":"4",
         "target":"10406",
         "relatedness":"0.5503500735626715"
      },
      {
         "source":"4",
         "target":"9897",
         "relatedness":"0.5545702621279714"
      },
      {
         "source":"4",
         "target":"4157971",
         "relatedness":"0.6685053818366195"
      },
      {
         "source":"4",
         "target":"12569",
         "relatedness":"0.5076945802150157"
      },
      {
         "source":"4",
         "target":"243391",
         "relatedness":"0.5663574999876313"
      },
      {
         "source":"4",
         "target":"287852",
         "relatedness":"0.7082035784211762"
      },
      {
         "source":"4",
         "target":"174455",
         "relatedness":"0.6280298763706038"
      },
      {
         "source":"4",
         "target":"3729225",
         "relatedness":"0.615078751736452"
      },
      {
         "source":"4",
         "target":"42012",
         "relatedness":"0.6113977367633239"
      },
      {
         "source":"4",
         "target":"1219340",
         "relatedness":"0.8329221924326833"
      },
      {
         "source":"4",
         "target":"21830",
         "relatedness":"0.6148108390389497"
      },
      {
         "source":"4",
         "target":"78968",
         "relatedness":"0.6327842066146039"
      },
      {
         "source":"4",
         "target":"419686",
         "relatedness":"0.520627021892176"
      },
      {
         "source":"4",
         "target":"25140",
         "relatedness":"0.547908602027182"
      },
      {
         "source":"4",
         "target":"14125745",
         "relatedness":"0.8243732704627958"
      },
      {
         "source":"4",
         "target":"2221011",
         "relatedness":"0.6980816075426228"
      },
      {
         "source":"4",
         "target":"9734298",
         "relatedness":"0.7856466655207813"
      },
      {
         "source":"4",
         "target":"17832909",
         "relatedness":"0.8061062961994516"
      },
      {
         "source":"4",
         "target":"1219317",
         "relatedness":"0.8433075749554192"
      },
      {
         "source":"4",
         "target":"208583",
         "relatedness":"0.7337695199036978"
      },
      {
         "source":"4",
         "target":"1462051",
         "relatedness":"0.7825460213116198"
      },
      {
         "source":"4",
         "target":"30365",
         "relatedness":"0.5636457527381235"
      },
      {
         "source":"4",
         "target":"37080",
         "relatedness":"0.5931268585805346"
      },
      {
         "source":"4",
         "target":"49901",
         "relatedness":"0.7149640194822738"
      },
      {
         "source":"4",
         "target":"171850",
         "relatedness":"0.8104209407476685"
      }
   ]
}